[
  {
    "name": "Get Started",
    "folder": "/static/docs/get-started",
    "indexFile": "get-started.md",
    "files": [
      "agenda.md",
      "install.md",
      "initialize.md",
      "configure.md",
      "add-files.md",
      "share-data.md",
      "retrieve-data.md",
      "connect-code-and-data.md",
      "pipeline.md",
      "visualize.md",
      "reproduce.md",
      "metrics.md",
      "experiments.md",
      "compare-experiments.md",
      "older-versions.md",
      "example-versioning.md",
      "example-pipeline.md"
    ],
    "labels": {
      "agenda.md": "Agenda"
    }
  },
  {
    "name": "Use Cases",
    "folder": "/static/docs/use-cases",
    "indexFile": "use-cases.md",
    "files": [
      "data-and-model-files-versioning.md",
      "share-data-and-model-files.md",
      "multiple-data-scientists-on-a-single-machine.md"
    ]
  },
  {
    "name": "User Guide",
    "folder": "/static/docs/user-guide",
    "files": [
      "dvc-files-and-directories.md",
      "dvc-file-format.md",
      "cache-file-linking.md",
      "external-dependencies.md",
      "external-outputs.md",
      "development.md",
      "contributing.md",
      "contributing-documentation.md",
      "update-tracked-file.md",
      "autocomplete.md",
      "plugins.md",
      "analytics.md",
      "dvcignore.md"
    ]
  },
  {
    "name": "Commands Reference",
    "folder": "/static/docs/commands-reference",
    "indexFile": "commands-reference.md",
    "files": [
      "add.md",
      {
        "name": "cache",
        "folder": "/static/docs/commands-reference/cache",
        "indexFile": "cache.md",
        "files": ["dir.md"]
      },
      "checkout.md",
      "commit.md",
      "config.md",
      "diff.md",
      "destroy.md",
      "fetch.md",
      "gc.md",
      "init.md",
      "install.md",
      "import.md",
      "lock.md",
      {
        "name": "metrics",
        "folder": "/static/docs/commands-reference/metrics",
        "indexFile": "metrics.md",
        "files": ["add.md", "modify.md", "remove.md", "show.md"],
        "labels": {
          "remove.md": "remove"
        }
      },
      "move.md",
      {
        "name": "pipeline",
        "folder": "/static/docs/commands-reference/pipeline",
        "indexFile": "pipeline.md",
        "files": ["list.md", "show.md"]
      },
      "push.md",
      "pull.md",
      {
        "name": "remote",
        "indexFile": "remote.md",
        "folder": "/static/docs/commands-reference/remote",
        "files": ["add.md", "default.md", "list.md", "modify.md", "remove.md"]
      },
      "remove.md",
      "repro.md",
      "root.md",
      "run.md",
      "status.md",
      "unlock.md",
      "unprotect.md",
      "version.md"
    ]
  },
  {
    "name": "Tutorial",
    "folder": "/static/docs/tutorial",
    "indexFile": "tutorial.md",
    "files": [
      "preparation.md",
      "define-ml-pipeline.md",
      "reproducibility.md",
      "sharing-data.md"
    ]
  },
  {
    "name": "Understanding Dvc",
    "folder": "/static/docs/understanding-dvc",
    "files": [
      "collaboration-issues.md",
      "existing-tools.md",
      "what-is-dvc.md",
      "core-features.md",
      "how-it-works.md",
      "related-technologies.md",
      "resources.md"
    ]
  },
  {
    "name": "Changelog",
    "folder": "/static/docs/changelog",
    "files": ["0.35.md", "0.18.md"]
  }
]
