[
  {
    "slug": "",
    "label": "DVC Docs Home",
    "icon": "house"
  },
  {
    "slug": "install",
    "children": [
      {
        "slug": "macos",
        "label": "macOS"
      },
      "windows",
      "linux",
      {
        "slug": "pre-release",
        "label": "Pre-release Version"
      },
      {
        "slug": "completion",
        "label": "Shell Completion"
      },
      "plugins"
    ]
  },
  {
    "slug": "start",
    "label": "Get Started",
    "tutorials": {
      "katacoda": "https://katacoda.com/dvc/courses/get-started"
    },
    "children": [
      {
        "slug": "data-management",
        "children": [
          {
            "slug": "access",
            "label": "Data and Model Access",
            "tutorials": {
              "katacoda": "https://katacoda.com/dvc/courses/get-started/accessing"
            }
          },
          {
            "slug": "pipelines",
            "label": "Data Pipelines",
            "tutorials": {
              "katacoda": "https://katacoda.com/dvc/courses/get-started/stages"
            }
          },
          {
            "slug": "metrics-parameters-plots",
            "label": "Metrics, Parameters, and Plots",
            "tutorials": {
              "katacoda": "https://katacoda.com/dvc/courses/get-started/params-metrics-plots"
            }
          }
        ]
      },
      {
        "slug": "experiments",
        "tutorials": {
          "katacoda": "https://katacoda.com/dvc/courses/get-started/experiments"
        },
        "children": [
          {
            "label": "Visualization",
            "slug": "visualization",
            "tutorials": {
              "katacoda": "https://katacoda.com/dvc/courses/get-started/params-metrics-plots"
            }
          }
        ]
      }
    ]
  },
  {
    "slug": "use-cases",
    "source": "use-cases/index.md",
    "children": [
      {
        "slug": "versioning-data-and-models",
        "children": [
          {
            "label": "Tutorial 👩‍💻",
            "slug": "tutorial"
          }
        ]
      },
      {
        "slug": "fast-data-caching-hub",
        "label": "Fast and Secure Data Caching Hub"
      },
      "data-registry",
      {
        "slug": "ci-cd-for-machine-learning",
        "label": "CI/CD for Machine Learning"
      },
      "ml-experiment-tracking",
      "ml-model-registry"
    ]
  },
  {
    "slug": "user-guide",
    "source": false,
    "children": [
      {
        "slug": "what-is-dvc",
        "label": "What is DVC?"
      },
      {
        "slug": "project-structure",
        "children": [
          {
            "slug": "pipelines-files",
            "label": "Pipelines Files (dvc.yaml)"
          },
          {
            "slug": "dvc-files",
            "label": ".dvc Files"
          },
          {
            "slug": "dvcignore-files",
            "label": ".dvcignore Files",
            "tutorials": {
              "katacoda": "https://katacoda.com/dvc/courses/examples/dvcignore"
            }
          },
          {
            "slug": "internal-files",
            "label": "Internal Directories and Files"
          }
        ]
      },
      {
        "slug": "experiment-management",
        "children": [
          "experiments-overview",
          "running-experiments",
          {
            "slug": "comparing-experiments",
            "label": "Reviewing and Comparing"
          },
          "sharing-experiments",
          "persisting-experiments",
          "cleaning-experiments",
          "checkpoints"
        ]
      },
      {
        "slug": "how-to",
        "source": false,
        "children": [
          "stop-tracking-data",
          "update-tracked-data",
          "add-stage-deps-or-outs",
          "merge-git-conflicts",
          "share-a-dvc-cache"
        ]
      },
      "setup-google-drive-remote",
      "large-dataset-optimization",
      "external-dependencies",
      "managing-external-data",
      "running-dvc-on-windows",
      "troubleshooting",
      "related-technologies",
      {
        "slug": "analytics",
        "label": "Anonymized Usage Analytics"
      },
      {
        "slug": "glossary",
        "source": "basic-concepts"
      }
    ]
  },
  {
    "slug": "command-reference",
    "children": [
      {
        "slug": "add",
        "label": "add"
      },
      {
        "slug": "cache",
        "label": "cache",
        "children": [
          {
            "slug": "dir",
            "label": "cache dir"
          }
        ]
      },
      {
        "slug": "check-ignore",
        "label": "check-ignore"
      },
      {
        "slug": "checkout",
        "label": "checkout"
      },
      {
        "slug": "commit",
        "label": "commit"
      },
      {
        "slug": "config",
        "label": "config"
      },
      {
        "slug": "dag",
        "label": "dag"
      },
      {
        "slug": "destroy",
        "label": "destroy"
      },
      {
        "slug": "diff",
        "label": "diff"
      },
      {
        "slug": "doctor",
        "label": "doctor"
      },
      {
        "slug": "exp",
        "label": "exp",
        "children": [
          {
            "slug": "init",
            "label": "exp init"
          },
          {
            "slug": "run",
            "label": "exp run"
          },
          {
            "slug": "show",
            "label": "exp show"
          },
          {
            "slug": "diff",
            "label": "exp diff"
          },
          {
            "slug": "list",
            "label": "exp list"
          },
          {
            "slug": "apply",
            "label": "exp apply"
          },
          {
            "slug": "branch",
            "label": "exp branch"
          },
          {
            "slug": "remove",
            "label": "exp remove"
          },
          {
            "slug": "gc",
            "label": "exp gc"
          },
          {
            "slug": "push",
            "label": "exp push"
          },
          {
            "slug": "pull",
            "label": "exp pull"
          }
        ]
      },
      {
        "slug": "fetch",
        "label": "fetch",
        "tutorials": {
          "katacoda": "https://katacoda.com/dvc/courses/examples/fetch"
        }
      },
      {
        "slug": "freeze",
        "label": "freeze"
      },
      {
        "slug": "gc",
        "label": "gc"
      },
      {
        "slug": "get-url",
        "label": "get-url"
      },
      {
        "slug": "get",
        "label": "get"
      },
      {
        "slug": "import-url",
        "label": "import-url"
      },
      {
        "slug": "import",
        "label": "import"
      },
      {
        "slug": "init",
        "label": "init"
      },
      {
        "slug": "install",
        "label": "install"
      },
      {
        "slug": "list",
        "label": "list"
      },
      {
        "slug": "metrics",
        "label": "metrics",
        "children": [
          {
            "slug": "show",
            "label": "metrics show"
          },
          {
            "slug": "diff",
            "label": "metrics diff"
          }
        ]
      },
      {
        "slug": "move",
        "label": "move"
      },
      {
        "slug": "params",
        "label": "params",
        "children": [
          {
            "slug": "diff",
            "label": "params diff"
          }
        ]
      },
      {
        "slug": "plots",
        "label": "plots",
        "children": [
          {
            "slug": "show",
            "label": "plots show"
          },
          {
            "slug": "diff",
            "label": "plots diff"
          },
          {
            "slug": "modify",
            "label": "plots modify"
          }
        ]
      },
      {
        "slug": "pull",
        "label": "pull"
      },
      {
        "slug": "push",
        "label": "push"
      },
      {
        "slug": "remote",
        "label": "remote",
        "children": [
          {
            "slug": "add",
            "label": "remote add"
          },
          {
            "slug": "modify",
            "label": "remote modify"
          },
          {
            "slug": "default",
            "label": "remote default"
          },
          {
            "slug": "list",
            "label": "remote list"
          },
          {
            "slug": "remove",
            "label": "remote remove"
          },
          {
            "slug": "rename",
            "label": "remote rename"
          }
        ]
      },
      {
        "slug": "remove",
        "label": "remove"
      },
      {
        "slug": "repro",
        "label": "repro"
      },
      {
        "slug": "root",
        "label": "root"
      },
      {
        "slug": "run",
        "label": "run"
      },
      {
        "slug": "stage",
        "label": "stage",
        "children": [
          {
            "slug": "add",
            "label": "stage add"
          },
          {
            "slug": "list",
            "label": "stage list"
          }
        ]
      },
      {
        "slug": "status",
        "label": "status"
      },
      {
        "slug": "unfreeze",
        "label": "unfreeze"
      },
      {
        "slug": "unprotect",
        "label": "unprotect"
      },
      {
        "slug": "update",
        "label": "update"
      },
      {
        "slug": "version",
        "label": "version"
      }
    ]
  },
  {
    "slug": "api-reference",
    "label": "Python API Reference",
    "children": [
      {
        "slug": "get_url",
        "label": "get_url()"
      },
      {
        "slug": "open",
        "label": "open()"
      },
      {
        "slug": "read",
        "label": "read()"
      },
      {
        "slug": "make_checkpoint",
        "label": "make_checkpoint()"
      }
    ]
  },
  {
    "slug": "contributing",
    "source": false,
    "children": [
      {
        "slug": "core",
        "label": "DVC Core Project"
      },
      {
        "slug": "docs",
        "label": "Documentation"
      },
      {
        "slug": "blog",
        "label": "Writing Blog Posts"
      }
    ]
  },
  {
    "label": "Changelog",
    "url": "https://github.com/iterative/dvc/releases",
    "type": "external"
  },
  {
    "slug": "cml",
    "icon": "cml",
    "url": "https://cml.dev/doc",
    "type": "external"
  },
  {
    "slug": "studio",
    "icon": "studio",
    "children": [
      {
        "slug": "how-it-works",
        "label": "How It Works"
      },
      "get-started",
      {
        "slug": "user-guide",
        "source": false,
        "children": [
          {
            "slug": "prepare-repositories",
            "label": "Prepare Your Repositories"
          },
          {
            "slug": "views",
            "label": "Views and Experiments",
            "source": false,
            "children": [
              "what-is-a-view",
              "create-a-view",
              {
                "slug": "view-settings",
                "label": "Configure a View"
              },
              {
                "slug": "explore-experiments",
                "label": "Explore ML Experiments"
              },
              {
                "slug": "visualize-experiments",
                "label": "Visualize and Compare"
              },
              "run-experiments",
              "share-a-view"
            ]
          },
          "teams",
          "change-team-plan-and-size",
          "account-management",
          "billing-and-payment",
          "install-github-app",
          "connect-custom-gitlab-server"
        ]
      },
      "troubleshooting"
    ]
  },
  {
    "slug": "dvclive",
    "label": "DVCLive",
    "children": [
      {
        "slug": "get-started",
        "label": "Get Started"
      },
      {
        "slug": "dvclive-with-dvc",
        "label": "DVCLive with DVC"
      },
      {
        "slug": "ml-frameworks",
        "children": [
          "catalyst",
          {
            "slug": "fastai",
            "label": "Fast.ai"
          },
          "hugging-face",
          "keras",
          {
            "slug": "lightgbm",
            "label": "LightGBM"
          },
          {
            "slug": "mmcv",
            "label": "MMCV"
          },
          {
            "slug": "pytorch",
            "label": "PyTorch"
          },
          {
            "slug": "pytorch-lightning",
            "label": "PyTorch Lightning"
          },
          {
            "slug": "tensorflow",
            "label": "TensorFlow"
          },
          {
            "slug": "xgboost",
            "label": "XGBoost"
          }
        ]
      },
      {
        "slug": "api-reference",
        "children": [
          {
            "slug": "live",
            "label": "Live()",
            "children": [
              {
                "slug": "log",
                "label": "log()"
              },
              {
                "slug": "log_image",
                "label": "log_image()"
              },
              {
                "slug": "log_plot",
                "label": "log_plot()"
              },
              {
                "slug": "make_report",
                "label": "make_report()"
              },
              {
                "slug": "get_step",
                "label": "get_step()"
              },
              {
                "slug": "next_step",
                "label": "next_step()"
              },
              {
                "slug": "set_step",
                "label": "set_step()"
              }
            ]
          }
        ]
      }
    ]
  }
]
